{
  "source_csv": "Paletta_-_Portfolio_-_Dances_-_65a47faadc1efbe190055673---1a719687-ae42-4039-adaa-a8759d275139.csv",
  "folder": "collections/portfolio-dances/trauma-vs-obstacles",
  "slug": "trauma-vs-obstacles",
  "data": {
    "Name": "Trauma vs Obstacles",
    "Slug": "trauma-vs-obstacles",
    "Collection ID": "65a47faadc1efbe190055673",
    "Locale ID": "659a138155ab821f566b9e65",
    "Item ID": "65a47fb9edc0989cff521027",
    "Archived": "false",
    "Draft": "false",
    "Created On": "Mon Jan 15 2024 00:43:37 GMT+0000 (Coordinated Universal Time)",
    "Updated On": "Fri May 17 2024 20:04:16 GMT+0000 (Coordinated Universal Time)",
    "Published On": "Fri May 17 2024 20:04:20 GMT+0000 (Coordinated Universal Time)",
    "Main Image": "https://uploads-ssl.webflow.com/6593930a237f27f93f2dd6c8/661223094a4a7f0e1c7ee352_Screenshot%202024-04-06%20at%209.32.12%20PM.png",
    "Header": "Trauma vs Obstacles",
    "Description": "It encapsulates the complexity of my emotions regarding my homeland and the challenges of living far from it amidst the diaspora.",
    "Short Description": "It encapsulates the complexity of my emotions regarding my homeland and the challenges of living far from it amidst the diaspora. Funded by SKarts. ",
    "Dance Video Link": "https://vimeo.com/902837198",
    "Highlight?": "false"
  },
  "referenced_urls": [
    "https://uploads-ssl.webflow.com/6593930a237f27f93f2dd6c8/661223094a4a7f0e1c7ee352_Screenshot%202024-04-06%20at%209.32.12%20PM.png",
    "https://vimeo.com/902837198"
  ]
}